nxcurve.py
nxcurve-0.6.2.dist-info/LICENSE
nxcurve-0.6.2.dist-info/METADATA
nxcurve-0.6.2.dist-info/WHEEL
nxcurve-0.6.2.dist-info/top_level.txt
nxcurve-0.6.2.dist-info/RECORD
