Metadata-Version: 2.1
Name: nxcurve
Version: 0.6.2
Summary: draws RNS,QNX and BNX curves and their auc
Home-page: https://github.com/tardigrade33/nxcurve
Author: Nicolas Marin
Author-email: josue.marin1729@gmail.com
License: MIT
Keywords: RNX,qualitycurve,QNX,BNX
Platform: UNKNOWN
Classifier: Development Status :: 4 - Beta 
Classifier: License :: OSI Approved :: MIT License
Classifier: Programming Language :: Python :: 3.9
Requires-Dist: numpy
Requires-Dist: matplotlib
Requires-Dist: scikit-learn
